duration/__init__.py
duration/exceptions.py
duration-1.1.1.dist-info/DESCRIPTION.rst
duration-1.1.1.dist-info/METADATA
duration-1.1.1.dist-info/RECORD
duration-1.1.1.dist-info/WHEEL
duration-1.1.1.dist-info/metadata.json
duration-1.1.1.dist-info/top_level.txt
